skelevision/__init__.py
skelevision/exceptions.py
skelevision/miners.py
skelevision/objects.py
skelevision/utils.py
tests/__init__.py
tests/test_miners.py
tests/test_objects.py
tests/test_utils.py
tests/datasets/__init__.py
skelevision-0.1.5.dist-info/LICENSE
skelevision-0.1.5.dist-info/METADATA
skelevision-0.1.5.dist-info/WHEEL
skelevision-0.1.5.dist-info/top_level.txt
skelevision-0.1.5.dist-info/RECORD
