Metadata-Version: 2.1
Name: skelevision
Version: 0.1.5
Summary: Log Skeleton Visualizer and Browser
Home-page: https://github.com/RCoanda/skelevision
License: UNKNOWN
Platform: UNKNOWN
Classifier: Programming Language :: Python :: 3
Classifier: License :: OSI Approved :: BSD License
Classifier: Operating System :: OS Independent
Requires-Python: >=3.7
